[
  {
    "type": "Programe Language",
    "items": [
      {
        "type": "JS",
        "img": "/access/imgs/"
      }
    ]
  },
  {
    "type": "Frameworks",
    "items": [
      {
        "type": "React-JS",
        "img": "/access/imgs/"
      }
    ]
  },
  {
    "type": "Tools",
    "items": [
      {
        "type": "Visual Studio Code",
        "img": "/access/imgs/"
      }
    ]
  },
  {
    "type": "Cmd",
    "items": [
      {
        "type": "Git",
        "img": "/access/imgs/"
      }
    ]
  }
]
